burlslamtec/__init__.py
burlslamtec/sdk/Irrlicht_W.dll
burlslamtec/sdk/burl.exe
burlslamtec/sdk/d3dcompiler_47.dll
burlslamtec/sdk/dnssd.dll
burlslamtec/sdk/ffmpeg.dll
burlslamtec/sdk/libEGL.dll
burlslamtec/sdk/libGLESv2.dll
burlslamtec/sdk/libblas.dll
burlslamtec/sdk/libeay32.dll
burlslamtec/sdk/libgcc_s_dw2-1.dll
burlslamtec/sdk/libgfortran-3.dll
burlslamtec/sdk/liblapack.dll
burlslamtec/sdk/libquadmath-0.dll
burlslamtec/sdk/libusb-1.0.dll
burlslamtec/sdk/msvcp100.dll
burlslamtec/sdk/msvcp100d.dll
burlslamtec/sdk/msvcr100.dll
burlslamtec/sdk/msvcr100d.dll
burlslamtec/sdk/ssleay32.dll
burlslamtec/sdk/vk_swiftshader.dll
burlslamtec/sdk/vulkan-1.dll
burlslamtec-0.0.5.dist-info/METADATA
burlslamtec-0.0.5.dist-info/WHEEL
burlslamtec-0.0.5.dist-info/top_level.txt
burlslamtec-0.0.5.dist-info/RECORD
