Metadata-Version: 2.1
Name: burlslamtec
Version: 0.0.5
Summary: develop by tanawat thuamthet
Home-page: UNKNOWN
Author: UNKNOWN
Author-email: tempkakao@gmail.com
License: tempkakao
Keywords: burlslamtec
Platform: UNKNOWN
